fugue_blazing/__init__.py
fugue_blazing/_io.py
fugue_blazing/_utils.py
fugue_blazing/dataframe.py
fugue_blazing/execution_engine.py
fugue_blazing_version/__init__.py
tests/__init__.py
tests/cpu/__init__.py
tests/cpu/fugue_blazing/__init__.py
tests/cpu/fugue_blazing/test_placeholder.py
tests/gpu/__init__.py
tests/gpu/fugue_blazing/__init__.py
tests/gpu/fugue_blazing/test_dataframe.py
tests/gpu/fugue_blazing/test_execution_engine.py
tests/gpu/fugue_blazing/test_io.py
fugue_blazing-0.0.3.dist-info/LICENSE
fugue_blazing-0.0.3.dist-info/METADATA
fugue_blazing-0.0.3.dist-info/WHEEL
fugue_blazing-0.0.3.dist-info/top_level.txt
fugue_blazing-0.0.3.dist-info/RECORD
