Metadata-Version: 2.1
Name: fugue-blazing
Version: 0.0.3
Summary: Fugue, Rapids, BlazingSQL integration
Home-page: http://github.com/fugue-project/fugue-blazing
Author: Han Wang
Author-email: goodwanghan@gmail.com
License: Apache-2.0
Keywords: fugue rapids ai blazing sql blazingsql
Platform: UNKNOWN
Classifier: Development Status :: 4 - Beta
Classifier: Intended Audience :: Developers
Classifier: Topic :: Software Development :: Libraries :: Python Modules
Classifier: License :: OSI Approved :: Apache Software License
Classifier: Programming Language :: Python :: 3.6
Classifier: Programming Language :: Python :: 3.7
Classifier: Programming Language :: Python :: 3.8
Classifier: Programming Language :: Python :: 3 :: Only
Requires-Python: >=3.6
Requires-Dist: fugue[sql] (>=0.5.6)
